hello.py
hello_huey.py
dearpyguidemo-0.1.0.dist-info/METADATA
dearpyguidemo-0.1.0.dist-info/WHEEL
dearpyguidemo-0.1.0.dist-info/top_level.txt
dearpyguidemo-0.1.0.dist-info/RECORD
