Metadata-Version: 2.4
Name: dearpyguidemo
Version: 0.1.0
Summary: Add your description here
Requires-Python: >=3.12
Requires-Dist: dearpygui>=2.1.0
Requires-Dist: huey>=2.5.3
Requires-Dist: matplotlib>=3.10.5
Requires-Dist: networkx>=3.5
Requires-Dist: tqdm>=4.67.1
